aiomisc_entrypoint/__init__.py
aiomisc_entrypoint/abstractions.py
aiomisc_entrypoint/entrypoint.py
aiomisc_entrypoint/processors/__init__.py
aiomisc_entrypoint/processors/change_user.py
aiomisc_entrypoint/processors/clear_environ.py
aiomisc_entrypoint/processors/svc_dependency.py
aiomisc_entrypoint/processors/svc_to_context.py
aiomisc_entrypoint/processors/sys_signals.py
aiomisc_entrypoint-1.2.0.dist-info/METADATA
aiomisc_entrypoint-1.2.0.dist-info/WHEEL
aiomisc_entrypoint-1.2.0.dist-info/RECORD
