Metadata-Version: 2.1
Name: aiomisc-entrypoint
Version: 1.2.0
Summary: 
Home-page: https://github.com/anysoft-kz/aiomisc-entrypoint
Author: Vladislav Vorobyov
Author-email: vladislav.vorobyov@gmail.com
Requires-Python: >=3.9,<4.0
Classifier: Programming Language :: Python :: 3
Classifier: Programming Language :: Python :: 3.9
Classifier: Programming Language :: Python :: 3.10
Classifier: Programming Language :: Python :: 3.11
Requires-Dist: aiomisc (>=16.0.0,<17.0.0)
Project-URL: Repository, https://github.com/anysoft-kz/aiomisc-entrypoint
